craigslist_reposter/__init__.py
craigslist_reposter/craigslist.py
craigslist_reposter/craigslist_email.py
craigslist_reposter/reposter.py
craigslist_reposter-0.2.2.dist-info/LICENSE
craigslist_reposter-0.2.2.dist-info/METADATA
craigslist_reposter-0.2.2.dist-info/WHEEL
craigslist_reposter-0.2.2.dist-info/top_level.txt
craigslist_reposter-0.2.2.dist-info/RECORD
