Metadata-Version: 2.1
Name: craigslist_reposter
Version: 0.2.2
Summary: A package for renewing and reposting posts on craigslist.com.
Author: porkyc
Project-URL: Homepage, https://github.com/porkyc/craigslist-reposter
Classifier: Programming Language :: Python :: 3
Classifier: License :: OSI Approved :: MIT License
Classifier: Operating System :: OS Independent
Requires-Python: >=3.10
License-File: LICENSE
